grpc_accesslog/__init__.py
grpc_accesslog/_async_server.py
grpc_accesslog/_context.py
grpc_accesslog/_server.py
grpc_accesslog/handlers.py
grpc_accesslog/py.typed
grpc_accesslog-0.3.0.dist-info/LICENSE.rst
grpc_accesslog-0.3.0.dist-info/METADATA
grpc_accesslog-0.3.0.dist-info/WHEEL
grpc_accesslog-0.3.0.dist-info/entry_points.txt
grpc_accesslog-0.3.0.dist-info/RECORD
