Metadata-Version: 2.1
Name: grpc-accesslog
Version: 0.3.0
Summary: gRPC Access Log
Home-page: https://github.com/villainy/grpc-accesslog
License: MIT
Author: Michael Morgan
Author-email: git@morgan83.com
Requires-Python: >=3.9,<4.0
Classifier: Development Status :: 4 - Beta
Classifier: License :: OSI Approved :: MIT License
Classifier: Programming Language :: Python :: 3
Classifier: Programming Language :: Python :: 3.9
Classifier: Programming Language :: Python :: 3.10
Classifier: Programming Language :: Python :: 3.11
Requires-Dist: grpcio (>=1.56.2,<2.0.0)
Project-URL: Changelog, https://github.com/villainy/grpc-accesslog/releases
Project-URL: Documentation, https://grpc-accesslog.readthedocs.io
Project-URL: Repository, https://github.com/villainy/grpc-accesslog
